ebsdlab/__init__.py
ebsdlab/ebsd.py
ebsdlab/orientation.py
ebsdlab/quaternion.py
ebsdlab/rodrigues.py
ebsdlab/symmetry.py
ebsdlab-0.0.6.dist-info/licenses/LICENSE
ebsdlab-0.0.6.dist-info/METADATA
ebsdlab-0.0.6.dist-info/WHEEL
ebsdlab-0.0.6.dist-info/top_level.txt
ebsdlab-0.0.6.dist-info/RECORD
