Metadata-Version: 2.4
Name: ebsdlab
Version: 0.0.6
Summary: The EBSD Lab for Python
Home-page: https://github.com/micromechanics/ebsdlab.git
Author: Steffen Brinckmann, Alexander Hartmaier
Author-email: sbrinckm@gmail.com
License: MIT
Classifier: Programming Language :: Python
Classifier: License :: OSI Approved :: BSD License
Classifier: Programming Language :: Python :: 3
Requires-Python: >=3.10
License-File: LICENSE
Requires-Dist: pillow
Requires-Dist: numpy
Requires-Dist: scipy
Requires-Dist: matplotlib
Provides-Extra: devel
Requires-Dist: sphinx; extra == "devel"
Requires-Dist: jupyter_sphinx; extra == "devel"
Requires-Dist: sphinx_tabs; extra == "devel"
Requires-Dist: pytest; extra == "devel"
Requires-Dist: isort; extra == "devel"
Requires-Dist: mypy; extra == "devel"
Requires-Dist: pylint; extra == "devel"
Requires-Dist: pre-commit; extra == "devel"
Requires-Dist: requests; extra == "devel"
Requires-Dist: pip-tools; extra == "devel"
Dynamic: license-file
